AUTHOR.txt
CHANGES.txt
COPYRIGHT.txt
LICENSE.txt
README.txt
bootstrap.py
buildout.cfg
setup.py
src/z3c/__init__.py
src/z3c.tabular.egg-info/PKG-INFO
src/z3c.tabular.egg-info/SOURCES.txt
src/z3c.tabular.egg-info/dependency_links.txt
src/z3c.tabular.egg-info/namespace_packages.txt
src/z3c.tabular.egg-info/not-zip-safe
src/z3c.tabular.egg-info/requires.txt
src/z3c.tabular.egg-info/top_level.txt
src/z3c/tabular/README.txt
src/z3c/tabular/__init__.py
src/z3c/tabular/browser.zcml
src/z3c/tabular/configure.zcml
src/z3c/tabular/formtable.pt
src/z3c/tabular/interfaces.py
src/z3c/tabular/subformtable.pt
src/z3c/tabular/table.pt
src/z3c/tabular/table.py
src/z3c/tabular/testing.py
src/z3c/tabular/tests.py