Metadata-Version: 1.1
Name: z3c.tabular
Version: 0.6.2
Summary: Table with form support based on z3c.form and z3c.table for Zope3
Home-page: http://pypi.python.org/pypi/z3c.tabular
Author: Roger Ineichen and the Zope Community
Author-email: zope-dev@zope.org
License: ZPL 2.1
Keywords: zope3 z3c tabular data form table contents
Platform: UNKNOWN
Classifier: Development Status :: 4 - Beta
Classifier: Environment :: Web Environment
Classifier: Intended Audience :: Developers
Classifier: License :: OSI Approved :: Zope Public License
Classifier: Programming Language :: Python
Classifier: Natural Language :: English
Classifier: Operating System :: OS Independent
Classifier: Topic :: Internet :: WWW/HTTP
Classifier: Framework :: Zope3
